aigc_zoo/.gitignore
aigc_zoo/__init__.py
aigc_zoo/requirements.txt
aigc_zoo/constants/__init__.py
aigc_zoo/constants/define.py
aigc_zoo/generator_utils/__init__.py
aigc_zoo/generator_utils/generator_baichuan.py
aigc_zoo/generator_utils/generator_baichuan2.py
aigc_zoo/generator_utils/generator_base.py
aigc_zoo/generator_utils/generator_chatglm.py
aigc_zoo/generator_utils/generator_chatglm2.py
aigc_zoo/generator_utils/generator_internlm.py
aigc_zoo/generator_utils/generator_llm.py
aigc_zoo/generator_utils/generator_moss.py
aigc_zoo/generator_utils/generator_qwen.py
aigc_zoo/generator_utils/generator_rwkv4.py
aigc_zoo/generator_utils/generator_t5.py
aigc_zoo/generator_utils/generator_xverse.py
aigc_zoo/model_zoo/__init__.py
aigc_zoo/model_zoo/asr_ctc/__init__.py
aigc_zoo/model_zoo/asr_ctc/llm_model.py
aigc_zoo/model_zoo/asr_seq2seq/__init__.py
aigc_zoo/model_zoo/asr_seq2seq/llm_model.py
aigc_zoo/model_zoo/auto/__init__.py
aigc_zoo/model_zoo/auto/base_wapper.py
aigc_zoo/model_zoo/auto/dpo_model.py
aigc_zoo/model_zoo/auto/llm_model.py
aigc_zoo/model_zoo/auto/reward_model.py
aigc_zoo/model_zoo/auto/rrhf_model.py
aigc_zoo/model_zoo/baichuan/__init__.py
aigc_zoo/model_zoo/baichuan/baichuan2_13b/__init__.py
aigc_zoo/model_zoo/baichuan/baichuan2_13b/dpo_model.py
aigc_zoo/model_zoo/baichuan/baichuan2_13b/generation_utils.py
aigc_zoo/model_zoo/baichuan/baichuan2_13b/llm_model.py
aigc_zoo/model_zoo/baichuan/baichuan2_13b/tokenization_baichuan.py
aigc_zoo/model_zoo/baichuan/baichuan2_7b/__init__.py
aigc_zoo/model_zoo/baichuan/baichuan2_7b/dpo_model.py
aigc_zoo/model_zoo/baichuan/baichuan2_7b/generation_utils.py
aigc_zoo/model_zoo/baichuan/baichuan2_7b/llm_model.py
aigc_zoo/model_zoo/baichuan/baichuan2_7b/tokenization_baichuan.py
aigc_zoo/model_zoo/baichuan/baichuan_13b/__init__.py
aigc_zoo/model_zoo/baichuan/baichuan_13b/dpo_model.py
aigc_zoo/model_zoo/baichuan/baichuan_13b/llm_model.py
aigc_zoo/model_zoo/baichuan/baichuan_13b/tokenization_baichuan.py
aigc_zoo-0.2.11.dist-info/LICENSE
aigc_zoo-0.2.11.dist-info/METADATA
aigc_zoo-0.2.11.dist-info/WHEEL
aigc_zoo-0.2.11.dist-info/top_level.txt
aigc_zoo-0.2.11.dist-info/RECORD
