Metadata-Version: 2.1
Name: aigc-zoo
Version: 0.2.11
Summary: aigc zoo
Home-page: https://github.com/ssbuild/aigc_zoo
Author: ssbuild
Author-email: 9727464@qq.com
License: Apache License 2.0
License-File: LICENSE
Requires-Dist: deep-training (~=0.2.11)
